README
setup.cfg
setup.py
tgext/__init__.py
tgext.xmlrpc.egg-info/PKG-INFO
tgext.xmlrpc.egg-info/SOURCES.txt
tgext.xmlrpc.egg-info/dependency_links.txt
tgext.xmlrpc.egg-info/entry_points.txt
tgext.xmlrpc.egg-info/namespace_packages.txt
tgext.xmlrpc.egg-info/paster_plugins.txt
tgext.xmlrpc.egg-info/requires.txt
tgext.xmlrpc.egg-info/top_level.txt
tgext/xmlrpc/__init__.py
tgext/xmlrpc/controllers.py
tgext/xmlrpc/test/__init__.py
tgext/xmlrpc/test/test_controller.py
tgext/xmlrpc/test/controllers/__init__.py
tgext/xmlrpc/test/controllers/root.py
tgext/xmlrpc/test/lib/__init__.py
tgext/xmlrpc/test/lib/app_globals.py
tgext/xmlrpc/test/lib/base.py
tgext/xmlrpc/test/lib/helpers.py
tgext/xmlrpc/test/static/__init__.py
tgext/xmlrpc/test/templates/__init__.py