Metadata-Version: 1.0
Name: tgext.xmlrpc
Version: 1.0
Summary: TurboGears XMLRPC Controller
Home-page: http://bitbucker.org/pedersen/tgext.xmlrpc
Author: Michael J. Pedersen
Author-email: m.pedersen@icelus.org
License: UNKNOWN
Platform: UNKNOWN
